extrapython/__init__.py
extrapython/base64tools.py
extrapython/passwordtools.py
extrapython-0.0.2.dist-info/LICENSE
extrapython-0.0.2.dist-info/METADATA
extrapython-0.0.2.dist-info/WHEEL
extrapython-0.0.2.dist-info/top_level.txt
extrapython-0.0.2.dist-info/RECORD
