Metadata-Version: 2.1
Name: extrapython
Version: 0.0.2
Summary: Adds useful features
Author: lndrtech
License: MIT
Project-URL: GitHub, https://github.com/lndrdev/extrapython
Project-URL: Documentation, https://extrapython.readthedocs.io
Keywords: useful,extra,python,extrapython
Classifier: Development Status :: 5 - Production/Stable
Classifier: License :: OSI Approved :: MIT License
Classifier: Intended Audience :: Developers
Classifier: Operating System :: OS Independent
Classifier: Programming Language :: Python :: 3.9
Classifier: Programming Language :: Python :: 3.10
Classifier: Programming Language :: Python :: 3.11
Classifier: Programming Language :: Python :: 3.12
Requires-Python: >=3.9
License-File: LICENSE
